nsj_multi_database_lib/__init__.py
nsj_multi_database_lib/db_pool_config.py
nsj_multi_database_lib/decorator/__init__.py
nsj_multi_database_lib/decorator/multi_database.py
nsj_multi_database_lib/env_config.py
nsj_multi_database_lib/exception.py
nsj_multi_database_lib/injector_factory.py
nsj_multi_database_lib/service/database_service.py
nsj_multi_database_lib/settings.py
nsj_multi_database_lib-2.1.0.dist-info/METADATA
nsj_multi_database_lib-2.1.0.dist-info/WHEEL
nsj_multi_database_lib-2.1.0.dist-info/RECORD
