Metadata-Version: 2.4
Name: nsj-multi-database-lib
Version: 2.1.0
Summary: Modulo que permite o uso de múltiplos bancos de dados na mesma aplicação.
Author: Wallace Pinho
Author-email: wallacepinho@nasajon.com.br
Requires-Python: >=3.6,<4.0
Classifier: Programming Language :: Python :: 3
Classifier: Programming Language :: Python :: 3.6
Classifier: Programming Language :: Python :: 3.7
Classifier: Programming Language :: Python :: 3.8
Classifier: Programming Language :: Python :: 3.9
Classifier: Programming Language :: Python :: 3.10
Classifier: Programming Language :: Python :: 3.11
Classifier: Programming Language :: Python :: 3.12
Classifier: Programming Language :: Python :: 3.13
Classifier: Programming Language :: Python :: 3.14
Requires-Dist: Flask
Requires-Dist: SQLAlchemy (>=1.4.32,<2.0.0)
Requires-Dist: cryptography (==40.0.1)
Requires-Dist: nsj_flask_auth (>=0.5.7,<1.0.0)
Requires-Dist: nsj_gcf_utils (>=1.1.0,<2.0.0)
Requires-Dist: nsj_rest_lib (>=0.1.6,<7.0.0)
Requires-Dist: pg8000 (>=1.24.1,<2.0.0)
